lacam_v0/__init__.py
lacam_v0/datasets.py
lacam_v0/data/dados_disp.txt
lacam_v0-0.2.1.dist-info/METADATA
lacam_v0-0.2.1.dist-info/WHEEL
lacam_v0-0.2.1.dist-info/top_level.txt
lacam_v0-0.2.1.dist-info/RECORD
