Metadata-Version: 2.1
Name: lacam-v0
Version: 0.2.1
Summary: A test library to LACAM - UNIFESSPA
Author: Saullo
Author-email: saullo.guilherme7@unifesspa.edu.br
Classifier: Programming Language :: Python :: 3
Classifier: Operating System :: OS Independent
